allennlp_utils/__init__.py
allennlp_utils/data/__init__.py
allennlp_utils/data/dataset_reader.py
allennlp_utils/data/tokenizer.py
allennlp_utils-0.0.1.dev2.dist-info/LICENSE
allennlp_utils-0.0.1.dev2.dist-info/METADATA
allennlp_utils-0.0.1.dev2.dist-info/WHEEL
allennlp_utils-0.0.1.dev2.dist-info/top_level.txt
allennlp_utils-0.0.1.dev2.dist-info/RECORD
