Metadata-Version: 2.1
Name: allennlp-utils
Version: 0.0.1.dev2
Summary: allennlp practical code
Home-page: https://github.com/wj-Mcat/allennlp-utils
Author: wj-Mcat（吴京京）
Author-email: 1435130236@qq.com
License: Apache-2.0
Platform: UNKNOWN
Classifier: Programming Language :: Python :: 3.7
Classifier: License :: OSI Approved :: Apache Software License
Classifier: Operating System :: OS Independent
